{
    "view_para": {
        "theta": 359.88189697265625,
        "upRow": 338,
        "downRow": 443,
        "leftCol": 6,
        "rightCol": 532
    },
    "hsv_para": {
        "h_min": 0,
        "h_max": 180,
        "s_min": 0,
        "s_max": 255,
        "v_min": 130,
        "v_max": 186,
        "reverse": true
    },
    "filter_para": {
        "filter_flag": true,
        "fill_hole_flag": true,
        "erase_flag": false,
        "box": [
            [
                "area",
                20.0,
                99999.0
            ],
            [
                "Eccentricity",
                0.0,
                99999.0
            ],
            [
                "Orientation",
                -90.0,
                99999.0
            ],
            [
                "rect_w",
                0.0,
                99999.0
            ],
            [
                "rect_h",
                3.0,
                99999.0
            ],
            [
                "EquivDiameter",
                0.0,
                99999.0
            ],
            [
                "Extent",
                0.0,
                99999.0
            ],
            [
                "solidity",
                0.0,
                99999.0
            ],
            [
                "None",
                0.0,
                99999.0
            ],
            [
                "None",
                0.0,
                99999.0
            ],
            [
                "None",
                0.0,
                99999.0
            ],
            [
                "None",
                0.0,
                99999.0
            ],
            [
                "None",
                0.0,
                99999.0
            ],
            [
                "None",
                0.0,
                99999.0
            ],
            [
                "None",
                0.0,
                99999.0
            ]
        ]
    },
    "roi_list": [
        [
            144,
            2,
            228,
            105
        ]
    ],
    "calib": 4.33,
    "lane_list": [
        [
            8,
            20,
            523,
            20
        ],
        [
            10,
            34,
            523,
            35
        ],
        [
            4,
            51,
            523,
            51
        ],
        [
            7,
            67,
            524,
            70
        ],
        [
            7,
            83,
            521,
            84
        ]
    ],
    "lane_num": 6
}